{
    "config": {
        "0": {
            "key": "3vurGO3X18jh1B562Gmql3",
            "position": [
                -0.6915119876256758,
                -0.9336178861788538
            ],
            "rotation": -1.0
        },
        "1": {
            "key": "1Ku8p4jm9B8fa3v1Jw9eez",
            "position": [
                -0.8204700861842584,
                0.8370847461695485
            ],
            "rotation": -1.0
        },
        "2": {
            "key": "1SYooP97X0jhAt_oxKRgNG",
            "position": [
                0.6599484305452197,
                -0.2233174815026443
            ],
            "rotation": -1.0
        },
        "3": {
            "key": "0F8iaczdbFmRiwSD4Ff7UC",
            "position": [
                0.46481189851268656,
                -0.5608128601759175
            ],
            "rotation": -1.0
        },
        "4": {
            "key": "1zqpb5qy540vLT51qexZaE",
            "position": [
                -0.9137595696254915,
                -0.23015319177217242
            ],
            "rotation": -1.0
        },
        "5": {
            "key": "3h9qxECqjF_xseJP$nv7$q",
            "position": [
                0.19765929778933677,
                -0.818147696349817
            ],
            "rotation": -1.0
        }
    },
    "creator": "FactorySimLive"
}